Metadata-Version: 2.1
Name: brundeckrun
Version: 0.2.5
Summary: A Rundeck API Python client
Home-page: https://github.com/antillion/brundeckrun
Author: rundeckrun@mindmind.com
Author-email: rundeckrun@mindmind.com
Maintainer: Lambda Vector
Maintainer-email: pablo@ceruleanhq.com
License: http://creativecommons.org/licenses/by-sa/3.0/
Platform: UNKNOWN
Classifier: Development Status :: 4 - Beta
Classifier: Intended Audience :: Developers
Classifier: Intended Audience :: Information Technology
Classifier: Intended Audience :: System Administrators
Classifier: Operating System :: OS Independent
Classifier: Programming Language :: Python :: 2.7
Classifier: Programming Language :: Python :: 3.3
Classifier: Programming Language :: Python :: 3.4
Classifier: Programming Language :: Python :: 3.5
Classifier: Programming Language :: Python :: 3.6
Classifier: Programming Language :: Python :: 3.7
Classifier: Programming Language :: Python :: 3.8
Classifier: Topic :: System :: Software Distribution
Classifier: Topic :: System :: Systems Administration
Classifier: Topic :: Utilities
